{
    "key": "group_6790a3de74024",
    "title": "Plugin Store Page",
    "fields": [
        {
            "key": "field_6790aa5ed10ad",
            "label": "Hero image",
            "name": "hero_image",
            "aria-label": "",
            "type": "image",
            "instructions": "",
            "required": 0,
            "conditional_logic": 0,
            "wrapper": {
                "width": "",
                "class": "",
                "id": ""
            },
            "return_format": "array",
            "library": "all",
            "min_width": "",
            "min_height": "",
            "min_size": "",
            "max_width": "",
            "max_height": "",
            "max_size": "",
            "mime_types": "",
            "preview_size": "medium"
        },
        {
            "key": "field_6790a3df15dc1",
            "label": "Headline",
            "name": "headline",
            "aria-label": "",
            "type": "text",
            "instructions": "",
            "required": 0,
            "conditional_logic": 0,
            "wrapper": {
                "width": "",
                "class": "",
                "id": ""
            },
            "default_value": "",
            "maxlength": "",
            "placeholder": "",
            "prepend": "",
            "append": ""
        },
        {
            "key": "field_6790a4b115dc2",
            "label": "Sub headline",
            "name": "sub_headline",
            "aria-label": "",
            "type": "textarea",
            "instructions": "",
            "required": 0,
            "conditional_logic": 0,
            "wrapper": {
                "width": "",
                "class": "",
                "id": ""
            },
            "default_value": "",
            "maxlength": "",
            "rows": "",
            "placeholder": "",
            "new_lines": ""
        },
        {
            "key": "field_6799981b2d63b",
            "label": "Best Selling Plugins Block",
            "name": "best_selling_plugins_block",
            "aria-label": "",
            "type": "group",
            "instructions": "",
            "required": 0,
            "conditional_logic": 0,
            "wrapper": {
                "width": "",
                "class": "",
                "id": ""
            },
            "layout": "block",
            "sub_fields": [
                {
                    "key": "field_679b1f1779872",
                    "label": "Headline",
                    "name": "headline",
                    "aria-label": "",
                    "type": "text",
                    "instructions": "",
                    "required": 0,
                    "conditional_logic": 0,
                    "wrapper": {
                        "width": "",
                        "class": "",
                        "id": ""
                    },
                    "default_value": "",
                    "maxlength": "",
                    "placeholder": "",
                    "prepend": "",
                    "append": ""
                },
                {
                    "key": "field_679998b82d63c",
                    "label": "cover image",
                    "name": "cover_image",
                    "aria-label": "",
                    "type": "image",
                    "instructions": "",
                    "required": 0,
                    "conditional_logic": 0,
                    "wrapper": {
                        "width": "",
                        "class": "",
                        "id": ""
                    },
                    "return_format": "array",
                    "library": "all",
                    "min_width": "",
                    "min_height": "",
                    "min_size": "",
                    "max_width": "",
                    "max_height": "",
                    "max_size": "",
                    "mime_types": "",
                    "preview_size": "medium"
                },
                {
                    "key": "field_67999a3b2d63d",
                    "label": "Image overlay text",
                    "name": "image_overlay_text",
                    "aria-label": "",
                    "type": "text",
                    "instructions": "",
                    "required": 0,
                    "conditional_logic": 0,
                    "wrapper": {
                        "width": "",
                        "class": "",
                        "id": ""
                    },
                    "default_value": "",
                    "maxlength": "",
                    "placeholder": "",
                    "prepend": "",
                    "append": ""
                },
                {
                    "key": "field_67999a682d63e",
                    "label": "Link",
                    "name": "link",
                    "aria-label": "",
                    "type": "link",
                    "instructions": "",
                    "required": 0,
                    "conditional_logic": 0,
                    "wrapper": {
                        "width": "",
                        "class": "",
                        "id": ""
                    },
                    "return_format": "array"
                }
            ]
        },
        {
            "key": "field_6799f011e5f2e",
            "label": "Testimonials With Rating",
            "name": "testimonials_with_rating",
            "aria-label": "",
            "type": "group",
            "instructions": "",
            "required": 0,
            "conditional_logic": 0,
            "wrapper": {
                "width": "",
                "class": "",
                "id": ""
            },
            "layout": "block",
            "sub_fields": [
                {
                    "key": "field_6799ee47b5f53",
                    "label": "Title",
                    "name": "title",
                    "aria-label": "",
                    "type": "text",
                    "instructions": "",
                    "required": 0,
                    "conditional_logic": 0,
                    "wrapper": {
                        "width": "",
                        "class": "",
                        "id": ""
                    },
                    "default_value": "",
                    "maxlength": "",
                    "placeholder": "",
                    "prepend": "",
                    "append": ""
                },
                {
                    "key": "field_679a0fa814120",
                    "label": "Headline",
                    "name": "headline",
                    "aria-label": "",
                    "type": "text",
                    "instructions": "",
                    "required": 0,
                    "conditional_logic": 0,
                    "wrapper": {
                        "width": "",
                        "class": "",
                        "id": ""
                    },
                    "default_value": "",
                    "maxlength": "",
                    "placeholder": "",
                    "prepend": "",
                    "append": ""
                },
                {
                    "key": "field_6799ee47b5f54",
                    "label": "Posts",
                    "name": "posts",
                    "aria-label": "",
                    "type": "relationship",
                    "instructions": "",
                    "required": 0,
                    "conditional_logic": 0,
                    "wrapper": {
                        "width": "",
                        "class": "",
                        "id": ""
                    },
                    "post_type": [
                        "testimonial"
                    ],
                    "post_status": [
                        "publish"
                    ],
                    "taxonomy": "",
                    "filters": [
                        "search",
                        "post_type",
                        "taxonomy"
                    ],
                    "return_format": "object",
                    "min": "",
                    "max": "",
                    "elements": "",
                    "bidirectional": 0,
                    "bidirectional_target": []
                }
            ]
        },
        {
            "key": "field_679a1ce5f7900",
            "label": "Latest Plugins Block",
            "name": "latest_plugins_block",
            "aria-label": "",
            "type": "group",
            "instructions": "",
            "required": 0,
            "conditional_logic": 0,
            "wrapper": {
                "width": "",
                "class": "",
                "id": ""
            },
            "layout": "block",
            "sub_fields": [
                {
                    "key": "field_679b2032f665f",
                    "label": "Headline",
                    "name": "headline",
                    "aria-label": "",
                    "type": "text",
                    "instructions": "",
                    "required": 0,
                    "conditional_logic": 0,
                    "wrapper": {
                        "width": "",
                        "class": "",
                        "id": ""
                    },
                    "default_value": "",
                    "maxlength": "",
                    "placeholder": "",
                    "prepend": "",
                    "append": ""
                },
                {
                    "key": "field_679a1ce6f7901",
                    "label": "cover image",
                    "name": "cover_image",
                    "aria-label": "",
                    "type": "image",
                    "instructions": "",
                    "required": 0,
                    "conditional_logic": 0,
                    "wrapper": {
                        "width": "",
                        "class": "",
                        "id": ""
                    },
                    "return_format": "array",
                    "library": "all",
                    "min_width": "",
                    "min_height": "",
                    "min_size": "",
                    "max_width": "",
                    "max_height": "",
                    "max_size": "",
                    "mime_types": "",
                    "preview_size": "medium"
                },
                {
                    "key": "field_679a1ce6f7902",
                    "label": "Image overlay text",
                    "name": "image_overlay_text",
                    "aria-label": "",
                    "type": "text",
                    "instructions": "",
                    "required": 0,
                    "conditional_logic": 0,
                    "wrapper": {
                        "width": "",
                        "class": "",
                        "id": ""
                    },
                    "default_value": "",
                    "maxlength": "",
                    "placeholder": "",
                    "prepend": "",
                    "append": ""
                },
                {
                    "key": "field_679a1ce6f7903",
                    "label": "Link",
                    "name": "link",
                    "aria-label": "",
                    "type": "link",
                    "instructions": "",
                    "required": 0,
                    "conditional_logic": 0,
                    "wrapper": {
                        "width": "",
                        "class": "",
                        "id": ""
                    },
                    "return_format": "array"
                }
            ]
        },
        {
            "key": "field_679a52ef1ae93",
            "label": "CTA Block",
            "name": "cta_block",
            "aria-label": "",
            "type": "group",
            "instructions": "",
            "required": 0,
            "conditional_logic": 0,
            "wrapper": {
                "width": "",
                "class": "",
                "id": ""
            },
            "layout": "block",
            "sub_fields": [
                {
                    "key": "field_679a53041ae94",
                    "label": "Background Image",
                    "name": "background_image",
                    "aria-label": "",
                    "type": "image",
                    "instructions": "",
                    "required": 0,
                    "conditional_logic": 0,
                    "wrapper": {
                        "width": "",
                        "class": "",
                        "id": ""
                    },
                    "return_format": "array",
                    "library": "all",
                    "min_width": "",
                    "min_height": "",
                    "min_size": "",
                    "max_width": "",
                    "max_height": "",
                    "max_size": "",
                    "mime_types": "",
                    "preview_size": "medium"
                },
                {
                    "key": "field_679a531c1ae95",
                    "label": "Headline",
                    "name": "headline",
                    "aria-label": "",
                    "type": "text",
                    "instructions": "",
                    "required": 0,
                    "conditional_logic": 0,
                    "wrapper": {
                        "width": "",
                        "class": "",
                        "id": ""
                    },
                    "default_value": "",
                    "maxlength": "",
                    "placeholder": "",
                    "prepend": "",
                    "append": ""
                },
                {
                    "key": "field_679a53451ae96",
                    "label": "Sub headline",
                    "name": "sub_headline",
                    "aria-label": "",
                    "type": "text",
                    "instructions": "",
                    "required": 0,
                    "conditional_logic": 0,
                    "wrapper": {
                        "width": "",
                        "class": "",
                        "id": ""
                    },
                    "default_value": "",
                    "maxlength": "",
                    "placeholder": "",
                    "prepend": "",
                    "append": ""
                },
                {
                    "key": "field_679a53501ae97",
                    "label": "Button",
                    "name": "button",
                    "aria-label": "",
                    "type": "link",
                    "instructions": "",
                    "required": 0,
                    "conditional_logic": 0,
                    "wrapper": {
                        "width": "",
                        "class": "",
                        "id": ""
                    },
                    "return_format": "array"
                }
            ]
        }
    ],
    "location": [
        [
            {
                "param": "page_template",
                "operator": "==",
                "value": "archive-products.php"
            }
        ]
    ],
    "menu_order": 0,
    "position": "normal",
    "style": "default",
    "label_placement": "top",
    "instruction_placement": "label",
    "hide_on_screen": "",
    "active": true,
    "description": "",
    "show_in_rest": 0,
    "modified": 1738219600
}
